zignal/__init__.py
zignal/__init__.pyi
zignal/_zignal.cpython-310-darwin.so
zignal/_zignal.pyi
zignal/py.typed
zignal_processing-0.9.1.dist-info/METADATA
zignal_processing-0.9.1.dist-info/WHEEL
zignal_processing-0.9.1.dist-info/top_level.txt
zignal_processing-0.9.1.dist-info/RECORD
