Metadata-Version: 2.4
Name: zignal-processing
Version: 0.9.1
Summary: Zero-dependency image processing library
Author: zignal contributors
License-Expression: MIT
Project-URL: Homepage, https://github.com/bfactory-ai/zignal
Project-URL: Repository, https://github.com/bfactory-ai/zignal
Project-URL: Documentation, https://bfactory-ai.github.io/zignal/python/zignal.html
Project-URL: Issues, https://github.com/bfactory-ai/zignal/issues
Keywords: image-processing,computer-vision,zig,native
Classifier: Development Status :: 4 - Beta
Classifier: Intended Audience :: Developers
Classifier: Programming Language :: Python :: 3
Classifier: Programming Language :: Python :: 3.10
Classifier: Programming Language :: Python :: 3.11
Classifier: Programming Language :: Python :: 3.12
Classifier: Programming Language :: Python :: 3.13
Classifier: Programming Language :: Python :: 3.14
Classifier: Topic :: Multimedia :: Graphics
Classifier: Topic :: Scientific/Engineering :: Image Processing
Requires-Python: >=3.10
Provides-Extra: test
Requires-Dist: pytest; extra == "test"
Requires-Dist: numpy; extra == "test"
Provides-Extra: docs
Requires-Dist: pdoc; extra == "docs"
